[{"isuGrade":"4","banNo":"1","isuGbNm":"전공심화","yungyukNm":"영역없음","suupNo2":"10623","haksuNo":"BIO3087","chgGwamokNm":"","gwamokNm":"최신생태과학기술세미나","suupMsg":"","abekGb":"N","hakwiNm":"학사","daepyoGangsaNm":"김백호","hakjeom":"2","ironSigan":"2","silsSigan":"0","suupTypeNm":"일반","jehanInwon":"15\/50","suupTimes":"월(14:30-16:30)","suupRoomNms":"서울 자연과학관 202강의실","isuJehanYn":"O","suupTypeGb":"","banSosokNm":"생명과학과","gnjSosokNm":"생명과학과"},{"isuGrade":"4","banNo":"1","isuGbNm":"전공심화","yungyukNm":"영역없음","suupNo2":"10624","haksuNo":"BIO4004","chgGwamokNm":"","gwamokNm":"진화생물학","suupMsg":"","abekGb":"N","hakwiNm":"학사","daepyoGangsaNm":"Ivana Karanovic","hakjeom":"3","ironSigan":"3","silsSigan":"0","suupTypeNm":"일반","jehanInwon":"47\/50","suupTimes":"월(10:30-12:00)\n목(14:30-16:00)","suupRoomNms":"서울 자연과학관 208강의실,서울 자연과학관 208강의실","isuJehanYn":"O","suupTypeGb":"영어전용","banSosokNm":"생명과학과","gnjSosokNm":"생명과학과"},{"isuGrade":"4","banNo":"1","isuGbNm":"전공핵심","yungyukNm":"영역없음","suupNo2":"10625","haksuNo":"BIO4021","chgGwamokNm":"","gwamokNm":"발생유전학","suupMsg":"","abekGb":"N","hakwiNm":"학사","daepyoGangsaNm":"심지원","hakjeom":"2","ironSigan":"2","silsSigan":"0","suupTypeNm":"일반","jehanInwon":"34\/50","suupTimes":"목(10:00-12:00)","suupRoomNms":"서울 자연과학관 B116강의실","isuJehanYn":"O","suupTypeGb":"영어전용","banSosokNm":"생명과학과","gnjSosokNm":"생명과학과"},{"isuGrade":"4","banNo":"1","isuGbNm":"전공심화","yungyukNm":"영역없음","suupNo2":"10626","haksuNo":"LIF3013","chgGwamokNm":"","gwamokNm":"생명과학심화연구캡스톤디자인1","suupMsg":"","abekGb":"N","hakwiNm":"학사","daepyoGangsaNm":"남진우","hakjeom":"1","ironSigan":"0","silsSigan":"2","suupTypeNm":"일반","jehanInwon":"29\/50","suupTimes":"시간미지정강좌","suupRoomNms":"비지정(서울)","isuJehanYn":"O","suupTypeGb":"","banSosokNm":"생명과학과","gnjSosokNm":"생명과학과"},{"isuGrade":"4","banNo":"1","isuGbNm":"전공심화","yungyukNm":"영역없음","suupNo2":"10627","haksuNo":"LIF4001","chgGwamokNm":"","gwamokNm":"바이오기술","suupMsg":"","abekGb":"N","hakwiNm":"학사","daepyoGangsaNm":"김영필","hakjeom":"3","ironSigan":"3","silsSigan":"0","suupTypeNm":"옴니버스","jehanInwon":"10\/40","suupTimes":"월(13:00-14:30)\n수(14:00-15:30)","suupRoomNms":"서울 자연과학관 205강의실,서울 자연과학관 205강의실","isuJehanYn":"O","suupTypeGb":"","banSosokNm":"생명과학과","gnjSosokNm":"생명과학과"},{"isuGrade":"4","banNo":"1","isuGbNm":"전공심화","yungyukNm":"영역없음","suupNo2":"10628","haksuNo":"LIF4002","chgGwamokNm":"","gwamokNm":"인체질병학개론","suupMsg":"","abekGb":"N","hakwiNm":"학사","daepyoGangsaNm":"최재훈","hakjeom":"2","ironSigan":"2","silsSigan":"0","suupTypeNm":"일반","jehanInwon":"28\/48","suupTimes":"화(13:00-15:00)","suupRoomNms":"서울 자연과학관 205강의실","isuJehanYn":"O","suupTypeGb":"","banSosokNm":"생명과학과","gnjSosokNm":"생명과학과"},{"isuGrade":"4","banNo":"1","isuGbNm":"전공심화","yungyukNm":"영역없음","suupNo2":"10629","haksuNo":"LIF4003","chgGwamokNm":"","gwamokNm":"생명과학야외실습3","suupMsg":"","abekGb":"N","hakwiNm":"학사","daepyoGangsaNm":"이원철","hakjeom":"1","ironSigan":"0","silsSigan":"2","suupTypeNm":"일반","jehanInwon":"21\/20","suupTimes":"시간미지정강좌","suupRoomNms":"비지정(서울)","isuJehanYn":"O","suupTypeGb":"","banSosokNm":"생명과학과","gnjSosokNm":"생명과학과"},{"isuGrade":"4","banNo":"1","isuGbNm":"전공심화","yungyukNm":"영역없음","suupNo2":"10630","haksuNo":"LIF4011","chgGwamokNm":"","gwamokNm":"생명과학세미나1","suupMsg":"","abekGb":"N","hakwiNm":"학사","daepyoGangsaNm":"김영필","hakjeom":"1","ironSigan":"1","silsSigan":"0","suupTypeNm":"일반","jehanInwon":"35\/50","suupTimes":"수(11:00-12:00)","suupRoomNms":"서울 자연과학관 B117강의실","isuJehanYn":"O","suupTypeGb":"","banSosokNm":"생명과학과","gnjSosokNm":"생명과학과"},{"isuGrade":"4","banNo":"1","isuGbNm":"전공심화","yungyukNm":"영역없음","suupNo2":"10632","haksuNo":"LIF4014","chgGwamokNm":"","gwamokNm":"면역학2","suupMsg":"","abekGb":"N","hakwiNm":"학사","daepyoGangsaNm":"최제민","hakjeom":"3","ironSigan":"3","silsSigan":"0","suupTypeNm":"일반","jehanInwon":"20\/25","suupTimes":"화(10:30-12:00)\n목(13:00-14:30)","suupRoomNms":"서울 자연과학관 205강의실,서울 자연과학관 205강의실","isuJehanYn":"O","suupTypeGb":"영어전용","banSosokNm":"생명과학과","gnjSosokNm":"생명과학과"}]