[{"isuGrade":"2","banNo":"1","isuGbNm":"전공핵심","yungyukNm":"영역없음","suupNo2":"10919","haksuNo":"CHE2001","chgGwamokNm":"","gwamokNm":"공업물리화학1","suupMsg":"","abekGb":"Y","hakwiNm":"학사","daepyoGangsaNm":"정재윤","hakjeom":"3","ironSigan":"3","silsSigan":"0","suupTypeNm":"일반","jehanInwon":"33\/45","suupTimes":"화(16:00-17:30)\n목(16:00-17:30)","suupRoomNms":"서울 제1공학관 504강의실,서울 제1공학관 504강의실","isuJehanYn":"O","suupTypeGb":"","banSosokNm":"유기나노공학과","gnjSosokNm":"유기나노공학과"},{"isuGrade":"2","banNo":"1","isuGbNm":"전공핵심","yungyukNm":"영역없음","suupNo2":"10931","haksuNo":"ICH2001","chgGwamokNm":"","gwamokNm":"공업유기화학1","suupMsg":"","abekGb":"Y","hakwiNm":"학사","daepyoGangsaNm":"조창기","hakjeom":"3","ironSigan":"3","silsSigan":"0","suupTypeNm":"일반","jehanInwon":"51\/50","suupTimes":"화(09:00-10:30)\n수(10:30-12:00)","suupRoomNms":"서울 제1공학관 203강의실,서울 제1공학관 402강의실","isuJehanYn":"O","suupTypeGb":"","banSosokNm":"유기나노공학과","gnjSosokNm":"유기나노공학과"},{"isuGrade":"2","banNo":"1","isuGbNm":"전공기초(필수)","yungyukNm":"영역없음","suupNo2":"10932","haksuNo":"MAT2017","chgGwamokNm":"","gwamokNm":"확률통계론","suupMsg":"","abekGb":"Y","hakwiNm":"학사","daepyoGangsaNm":"정성훈","hakjeom":"3","ironSigan":"3","silsSigan":"0","suupTypeNm":"일반","jehanInwon":"38\/35","suupTimes":"목(09:00-10:30)\n목(10:30-12:00)","suupRoomNms":"서울 제2공학관 정석현 PC 3,서울 제2공학관 정석현 PC 3","isuJehanYn":"O","suupTypeGb":"","banSosokNm":"유기나노공학과","gnjSosokNm":"유기나노공학과"},{"isuGrade":"2","banNo":"1","isuGbNm":"전공기초(필수)","yungyukNm":"영역없음","suupNo2":"12359","haksuNo":"COE3051","chgGwamokNm":"","gwamokNm":"공업수학1","suupMsg":"","abekGb":"Y","hakwiNm":"학사","daepyoGangsaNm":"김주형","hakjeom":"3","ironSigan":"3","silsSigan":"0","suupTypeNm":"일반","jehanInwon":"48\/43","suupTimes":"화(13:00-14:30)\n금(10:30-12:00)","suupRoomNms":"서울 제1공학관 205강의실,서울 제1공학관 205강의실","isuJehanYn":"O","suupTypeGb":"","banSosokNm":"유기나노공학과","gnjSosokNm":"공과대학 행정팀"}]