[{"isuGrade":"4","banNo":"1","isuGbNm":"전공심화","yungyukNm":"영역없음","suupNo2":"10423","haksuNo":"HIS2027","chgGwamokNm":"중국경제발전의역사","gwamokNm":"동아시아비교경제사","suupMsg":"","abekGb":"N","hakwiNm":"학사","daepyoGangsaNm":"강진아","hakjeom":"3","ironSigan":"3","silsSigan":"0","suupTypeNm":"일반","jehanInwon":"15\/35","suupTimes":"수(13:00-14:30)\n화(10:30-12:00)","suupRoomNms":"서울 인문관 305강의실,서울 인문관 305강의실","isuJehanYn":"O","suupTypeGb":"","banSosokNm":"사학과","gnjSosokNm":"사학과"},{"isuGrade":"4","banNo":"1","isuGbNm":"전공심화","yungyukNm":"영역없음","suupNo2":"10424","haksuNo":"HIS2065","chgGwamokNm":"","gwamokNm":"중국전통과학기술의역사적전개","suupMsg":"","abekGb":"N","hakwiNm":"학사","daepyoGangsaNm":"김성희","hakjeom":"3","ironSigan":"3","silsSigan":"0","suupTypeNm":"일반","jehanInwon":"19\/35","suupTimes":"수(09:30-11:00)\n금(09:30-11:00)","suupRoomNms":"서울 인문관 404강의실,서울 인문관 312강의실","isuJehanYn":"O","suupTypeGb":"","banSosokNm":"사학과","gnjSosokNm":"사학과"},{"isuGrade":"4","banNo":"1","isuGbNm":"전공심화","yungyukNm":"영역없음","suupNo2":"10425","haksuNo":"HIS3067","chgGwamokNm":"","gwamokNm":"문화유적답사Ⅱ","suupMsg":"","abekGb":"N","hakwiNm":"학사","daepyoGangsaNm":"이석규","hakjeom":"1","ironSigan":"0","silsSigan":"1","suupTypeNm":"일반","jehanInwon":"15\/25","suupTimes":"목(17:30-18:30)","suupRoomNms":"서울 인문관 405강의실","isuJehanYn":"O","suupTypeGb":"","banSosokNm":"사학과","gnjSosokNm":"사학과"},{"isuGrade":"4","banNo":"1","isuGbNm":"전공핵심","yungyukNm":"영역없음","suupNo2":"10426","haksuNo":"HIS4009","chgGwamokNm":"","gwamokNm":"한국현대사","suupMsg":"","abekGb":"N","hakwiNm":"학사","daepyoGangsaNm":"박동찬","hakjeom":"3","ironSigan":"3","silsSigan":"0","suupTypeNm":"일반","jehanInwon":"24\/35","suupTimes":"수(14:30-16:00)\n수(16:00-17:30)","suupRoomNms":"서울 인문관 116강의실,서울 인문관 116강의실","isuJehanYn":"O","suupTypeGb":"","banSosokNm":"사학과","gnjSosokNm":"사학과"},{"isuGrade":"4","banNo":"1","isuGbNm":"전공핵심","yungyukNm":"영역없음","suupNo2":"10427","haksuNo":"HIS4027","chgGwamokNm":"20세기중국:개혁과혁명","gwamokNm":"20세기세계와중국","suupMsg":"","abekGb":"N","hakwiNm":"학사","daepyoGangsaNm":"강진아","hakjeom":"3","ironSigan":"3","silsSigan":"0","suupTypeNm":"일반","jehanInwon":"23\/35","suupTimes":"월(13:00-14:30)\n화(13:00-14:30)","suupRoomNms":"서울 인문관 305강의실,서울 인문관 305강의실","isuJehanYn":"O","suupTypeGb":"","banSosokNm":"사학과","gnjSosokNm":"사학과"},{"isuGrade":"4","banNo":"1","isuGbNm":"전공핵심","yungyukNm":"영역없음","suupNo2":"10428","haksuNo":"HIS4034","chgGwamokNm":"","gwamokNm":"제노사이드의역사","suupMsg":"","abekGb":"N","hakwiNm":"학사","daepyoGangsaNm":"최정수","hakjeom":"3","ironSigan":"3","silsSigan":"0","suupTypeNm":"일반","jehanInwon":"16\/35","suupTimes":"월(14:30-16:00)\n월(16:00-17:30)","suupRoomNms":"서울 인문관 305강의실,서울 인문관 305강의실","isuJehanYn":"O","suupTypeGb":"","banSosokNm":"사학과","gnjSosokNm":"사학과"},{"isuGrade":"4","banNo":"1","isuGbNm":"전공핵심","yungyukNm":"영역없음","suupNo2":"10429","haksuNo":"HIS4061","chgGwamokNm":"","gwamokNm":"민족주의와제국주의","suupMsg":"","abekGb":"N","hakwiNm":"학사","daepyoGangsaNm":"최정수","hakjeom":"3","ironSigan":"3","silsSigan":"0","suupTypeNm":"일반","jehanInwon":"10\/35","suupTimes":"월(09:30-11:00)\n월(11:00-12:30)","suupRoomNms":"서울 인문관 305강의실,서울 인문관 305강의실","isuJehanYn":"O","suupTypeGb":"","banSosokNm":"사학과","gnjSosokNm":"사학과"},{"isuGrade":"4","banNo":"1","isuGbNm":"전공심화","yungyukNm":"영역없음","suupNo2":"10430","haksuNo":"HIS4063","chgGwamokNm":"","gwamokNm":"한국생활문화사","suupMsg":"","abekGb":"N","hakwiNm":"학사","daepyoGangsaNm":"주혁","hakjeom":"3","ironSigan":"3","silsSigan":"0","suupTypeNm":"일반","jehanInwon":"9\/35","suupTimes":"금(13:00-14:30)\n금(14:30-16:00)","suupRoomNms":"서울 인문관 302강의실,서울 인문관 302강의실","isuJehanYn":"O","suupTypeGb":"","banSosokNm":"사학과","gnjSosokNm":"사학과"},{"isuGrade":"4","banNo":"1","isuGbNm":"교직전공","yungyukNm":"영역없음","suupNo2":"10432","haksuNo":"TEA6006","chgGwamokNm":"","gwamokNm":"역사교과교재연구및지도","suupMsg":"","abekGb":"N","hakwiNm":"학사","daepyoGangsaNm":"신유아","hakjeom":"3","ironSigan":"3","silsSigan":"0","suupTypeNm":"일반","jehanInwon":"4\/8","suupTimes":"수(16:00-17:30)\n수(17:30-19:00)","suupRoomNms":"서울 인문관 401강의실,서울 인문관 401강의실","isuJehanYn":"O","suupTypeGb":"","banSosokNm":"사학과","gnjSosokNm":"사학과"},{"isuGrade":"4","banNo":"1","isuGbNm":"전공심화","yungyukNm":"영역없음","suupNo2":"12630","haksuNo":"HIS3065","chgGwamokNm":"","gwamokNm":"한국지성사","suupMsg":"","abekGb":"N","hakwiNm":"학사","daepyoGangsaNm":"이석규","hakjeom":"3","ironSigan":"3","silsSigan":"0","suupTypeNm":"일반","jehanInwon":"10\/35","suupTimes":"화(16:00-17:30)\n목(16:00-17:30)","suupRoomNms":"서울 인문관 405강의실,서울 인문관 405강의실","isuJehanYn":"O","suupTypeGb":"","banSosokNm":"사학과","gnjSosokNm":"사학과"}]