[{"isuGrade":"2","banNo":"1","isuGbNm":"전공기초(필수)","yungyukNm":"영역없음","suupNo2":"12038","haksuNo":"MAT2006","chgGwamokNm":"","gwamokNm":"정수론","suupMsg":"","abekGb":"N","hakwiNm":"학사","daepyoGangsaNm":"안상욱","hakjeom":"3","ironSigan":"3","silsSigan":"0","suupTypeNm":"일반","jehanInwon":"36\/40","suupTimes":"월(10:30-12:00)\n수(09:00-10:30)","suupRoomNms":"서울 자연과학관 202강의실,서울 자연과학관 202강의실","isuJehanYn":"O","suupTypeGb":"","banSosokNm":"수학과","gnjSosokNm":"수학과"},{"isuGrade":"2","banNo":"1","isuGbNm":"전공핵심","yungyukNm":"영역없음","suupNo2":"12039","haksuNo":"MAT2009","chgGwamokNm":"","gwamokNm":"미분방정식","suupMsg":"","abekGb":"N","hakwiNm":"학사","daepyoGangsaNm":"김승혁","hakjeom":"3","ironSigan":"3","silsSigan":"0","suupTypeNm":"일반","jehanInwon":"37\/35","suupTimes":"화(09:00-10:30)\n목(13:00-14:30)","suupRoomNms":"서울 자연과학관 B115강의실,서울 자연과학관 B115강의실","isuJehanYn":"O","suupTypeGb":"영어전용","banSosokNm":"수학과","gnjSosokNm":"수학과"},{"isuGrade":"2","banNo":"1","isuGbNm":"전공기초(필수)","yungyukNm":"영역없음","suupNo2":"12040","haksuNo":"MAT2015","chgGwamokNm":"","gwamokNm":"고등미적분학1","suupMsg":"","abekGb":"N","hakwiNm":"학사","daepyoGangsaNm":"박춘길","hakjeom":"3","ironSigan":"3","silsSigan":"0","suupTypeNm":"일반","jehanInwon":"46\/35","suupTimes":"화(10:30-12:00)\n목(14:30-16:00)","suupRoomNms":"서울 자연과학관 B115강의실,서울 자연과학관 B115강의실","isuJehanYn":"O","suupTypeGb":"","banSosokNm":"수학과","gnjSosokNm":"수학과"},{"isuGrade":"2","banNo":"1","isuGbNm":"전공핵심","yungyukNm":"영역없음","suupNo2":"12041","haksuNo":"MAT2022","chgGwamokNm":"","gwamokNm":"통계학의원리","suupMsg":"","abekGb":"N","hakwiNm":"학사","daepyoGangsaNm":"차경준","hakjeom":"3","ironSigan":"3","silsSigan":"0","suupTypeNm":"일반","jehanInwon":"43\/35","suupTimes":"월(13:00-14:30)\n수(10:30-12:00)","suupRoomNms":"서울 자연과학관 203강의실,서울 자연과학관 203강의실","isuJehanYn":"O","suupTypeGb":"","banSosokNm":"수학과","gnjSosokNm":"수학과"},{"isuGrade":"2","banNo":"1","isuGbNm":"전공기초(필수)","yungyukNm":"영역없음","suupNo2":"12042","haksuNo":"MAT2023","chgGwamokNm":"","gwamokNm":"선형대수1","suupMsg":"","abekGb":"N","hakwiNm":"학사","daepyoGangsaNm":"박홍구","hakjeom":"3","ironSigan":"3","silsSigan":"0","suupTypeNm":"일반","jehanInwon":"37\/30","suupTimes":"수(14:30-16:00)\n금(16:00-17:30)","suupRoomNms":"서울 자연과학관 226강의실,서울 자연과학관 226강의실","isuJehanYn":"O","suupTypeGb":"","banSosokNm":"수학과","gnjSosokNm":"수학과"},{"isuGrade":"2","banNo":"1","isuGbNm":"전공기초(필수)","yungyukNm":"영역없음","suupNo2":"13027","haksuNo":"MAT2015","chgGwamokNm":"","gwamokNm":"고등미적분학1","suupMsg":"","abekGb":"N","hakwiNm":"학사","daepyoGangsaNm":"박춘길","hakjeom":"3","ironSigan":"3","silsSigan":"0","suupTypeNm":"일반","jehanInwon":"29\/35","suupTimes":"화(14:30-16:00)\n목(10:30-12:00)","suupRoomNms":"서울 자연과학관 B115강의실,서울 자연과학관 B115강의실","isuJehanYn":"O","suupTypeGb":"","banSosokNm":"수학과","gnjSosokNm":"수학과"},{"isuGrade":"2","banNo":"1","isuGbNm":"전공기초(필수)","yungyukNm":"영역없음","suupNo2":"13028","haksuNo":"MAT2023","chgGwamokNm":"","gwamokNm":"선형대수1","suupMsg":"","abekGb":"N","hakwiNm":"학사","daepyoGangsaNm":"박홍구","hakjeom":"3","ironSigan":"3","silsSigan":"0","suupTypeNm":"일반","jehanInwon":"41\/30","suupTimes":"수(16:00-17:30)\n금(14:30-16:00)","suupRoomNms":"서울 자연과학관 226강의실,서울 자연과학관 226강의실","isuJehanYn":"O","suupTypeGb":"","banSosokNm":"수학과","gnjSosokNm":"수학과"},{"isuGrade":"2","banNo":"1","isuGbNm":"전공기초(필수)","yungyukNm":"영역없음","suupNo2":"13029","haksuNo":"MAT2006","chgGwamokNm":"","gwamokNm":"정수론","suupMsg":"","abekGb":"N","hakwiNm":"학사","daepyoGangsaNm":"서재홍","hakjeom":"3","ironSigan":"3","silsSigan":"0","suupTypeNm":"일반","jehanInwon":"34\/40","suupTimes":"월(16:00-17:30)\n금(10:30-12:00)","suupRoomNms":"서울 자연과학관 226강의실,서울 자연과학관 226강의실","isuJehanYn":"O","suupTypeGb":"","banSosokNm":"수학과","gnjSosokNm":"수학과"},{"isuGrade":"2","banNo":"1","isuGbNm":"전공핵심","yungyukNm":"영역없음","suupNo2":"13030","haksuNo":"MAT2009","chgGwamokNm":"","gwamokNm":"미분방정식","suupMsg":"","abekGb":"N","hakwiNm":"학사","daepyoGangsaNm":"김승혁","hakjeom":"3","ironSigan":"3","silsSigan":"0","suupTypeNm":"일반","jehanInwon":"31\/35","suupTimes":"화(13:00-14:30)\n목(09:00-10:30)","suupRoomNms":"서울 자연과학관 B115강의실,서울 자연과학관 B115강의실","isuJehanYn":"O","suupTypeGb":"영어전용","banSosokNm":"수학과","gnjSosokNm":"수학과"},{"isuGrade":"2","banNo":"1","isuGbNm":"전공핵심","yungyukNm":"영역없음","suupNo2":"13031","haksuNo":"MAT2022","chgGwamokNm":"","gwamokNm":"통계학의원리","suupMsg":"","abekGb":"N","hakwiNm":"학사","daepyoGangsaNm":"차경준","hakjeom":"3","ironSigan":"3","silsSigan":"0","suupTypeNm":"일반","jehanInwon":"41\/35","suupTimes":"월(14:30-16:00)\n수(13:00-14:30)","suupRoomNms":"서울 자연과학관 110강의실,서울 자연과학관 110강의실","isuJehanYn":"O","suupTypeGb":"","banSosokNm":"수학과","gnjSosokNm":"수학과"}]