[{"name":"유영만","daehakNm":"사범대학","hakgwaNm":"교육공학과","img_url":"https:\/\/portal.hanyang.ac.kr\/GwgsAct\/showImg.do?gaeinNo=ZIAOcUPmhsBhqjFjK9pV7w==","position":"교수","email":"010000@hanyang.ac.kr","office_phone":"02-2220-1126"},{"name":"안미리","daehakNm":"사범대학","hakgwaNm":"교육공학과","img_url":"https:\/\/portal.hanyang.ac.kr\/GwgsAct\/showImg.do?gaeinNo=L1\/KN3zkpo2NAp86rn1k7A==","position":"교수","email":"mlahn@hanyang.ac.kr","office_phone":"02-2220-1157"},{"name":"송지훈","daehakNm":"사범대학","hakgwaNm":"교육공학과","img_url":"https:\/\/portal.hanyang.ac.kr\/GwgsAct\/showImg.do?gaeinNo=HNU+DlTVHmzwd2R\/N0ykkg==","position":"부교수","email":"psu.jihoonsong@gmail.com","office_phone":"02-2220-2642"},{"name":"송영수","daehakNm":"사범대학","hakgwaNm":"교육공학과","img_url":"https:\/\/portal.hanyang.ac.kr\/GwgsAct\/showImg.do?gaeinNo=wyGaHmhFEJhE\/oaA8+8tMA==","position":"교수","email":"young2020@hanyang.ac.kr","office_phone":"02-2220-2740"},{"name":"김수정","daehakNm":"사범대학","hakgwaNm":"교육공학과","img_url":"https:\/\/portal.hanyang.ac.kr\/GwgsAct\/showImg.do?gaeinNo=9ghDmfB1MshvaU+jAlszFw==","position":"강사","email":"sjkim0624@gmail.com","office_phone":""},{"name":"최혜림","daehakNm":"사범대학","hakgwaNm":"교육공학과","img_url":"https:\/\/portal.hanyang.ac.kr\/GwgsAct\/showImg.do?gaeinNo=8uE0AGZHZU+T3Tl\/\/krFJQ==","position":"겸임교수","email":"hrchoi1103@hanyang.ac.kr","office_phone":"02-549-7501"}]