[{"isuGrade":"4","banNo":"1","isuGbNm":"전공심화","yungyukNm":"영역없음","suupNo2":"10657","haksuNo":"PHE2011","chgGwamokNm":"","gwamokNm":"체육사","suupMsg":"","abekGb":"N","hakwiNm":"학사","daepyoGangsaNm":"남궁영호","hakjeom":"2","ironSigan":"2","silsSigan":"0","suupTypeNm":"일반","jehanInwon":"19\/30","suupTimes":"금(13:00-15:00)","suupRoomNms":"서울 올림픽체육관 316강의실","isuJehanYn":"O","suupTypeGb":"","banSosokNm":"체육학과","gnjSosokNm":"체육학과"},{"isuGrade":"4","banNo":"1","isuGbNm":"전공핵심","yungyukNm":"영역없음","suupNo2":"10658","haksuNo":"PHE2096","chgGwamokNm":"","gwamokNm":"스포츠마사지","suupMsg":"","abekGb":"N","hakwiNm":"학사","daepyoGangsaNm":"손원호","hakjeom":"2","ironSigan":"2","silsSigan":"0","suupTypeNm":"일반","jehanInwon":"17\/30","suupTimes":"월(11:00-13:00)","suupRoomNms":"서울 올림픽체육관 302 세미나실","isuJehanYn":"O","suupTypeGb":"","banSosokNm":"체육학과","gnjSosokNm":"체육학과"},{"isuGrade":"4","banNo":"1","isuGbNm":"전공핵심","yungyukNm":"영역없음","suupNo2":"10659","haksuNo":"PHE5006","chgGwamokNm":"","gwamokNm":"체육학실험법","suupMsg":"","abekGb":"N","hakwiNm":"학사","daepyoGangsaNm":"오상덕","hakjeom":"2","ironSigan":"2","silsSigan":"0","suupTypeNm":"일반","jehanInwon":"19\/30","suupTimes":"수(11:00-13:00)","suupRoomNms":"서울 올림픽체육관 316강의실","isuJehanYn":"O","suupTypeGb":"","banSosokNm":"체육학과","gnjSosokNm":"체육학과"},{"isuGrade":"4","banNo":"1","isuGbNm":"전공심화","yungyukNm":"영역없음","suupNo2":"10660","haksuNo":"PHE5014","chgGwamokNm":"","gwamokNm":"운동부하검사및심전도","suupMsg":"","abekGb":"N","hakwiNm":"학사","daepyoGangsaNm":"조중연","hakjeom":"2","ironSigan":"2","silsSigan":"0","suupTypeNm":"일반","jehanInwon":"10\/33","suupTimes":"수(15:00-17:00)","suupRoomNms":"서울 올림픽체육관 316강의실","isuJehanYn":"O","suupTypeGb":"","banSosokNm":"체육학과","gnjSosokNm":"체육학과"},{"isuGrade":"4","banNo":"1","isuGbNm":"전공심화","yungyukNm":"영역없음","suupNo2":"10662","haksuNo":"PHE5037","chgGwamokNm":"","gwamokNm":"체육학실험연구캡스톤디자인I","suupMsg":"","abekGb":"N","hakwiNm":"학사","daepyoGangsaNm":"이성노","hakjeom":"1","ironSigan":"0","silsSigan":"1","suupTypeNm":"일반","jehanInwon":"16\/30","suupTimes":"수(13:00-14:00)","suupRoomNms":"서울 올림픽체육관 314강의실","isuJehanYn":"O","suupTypeGb":"","banSosokNm":"체육학과","gnjSosokNm":"체육학과"},{"isuGrade":"4","banNo":"1","isuGbNm":"교직전공","yungyukNm":"영역없음","suupNo2":"10665","haksuNo":"TEA6017","chgGwamokNm":"","gwamokNm":"체육교과교재연구및지도","suupMsg":"","abekGb":"N","hakwiNm":"학사","daepyoGangsaNm":"김정구","hakjeom":"3","ironSigan":"3","silsSigan":"0","suupTypeNm":"일반","jehanInwon":"7\/30","suupTimes":"목(17:00-18:30)\n목(18:30-20:00)","suupRoomNms":"서울 올림픽체육관 224강의실,서울 올림픽체육관 224강의실","isuJehanYn":"O","suupTypeGb":"","banSosokNm":"체육학과","gnjSosokNm":"체육학과"},{"isuGrade":"1","banNo":"1","isuGbNm":"전공기초(필수)","yungyukNm":"영역없음","suupNo2":"12161","haksuNo":"CUL3006","chgGwamokNm":"","gwamokNm":"웨이트트레이닝","suupMsg":"","abekGb":"N","hakwiNm":"학사","daepyoGangsaNm":"정재훈","hakjeom":"2","ironSigan":"0","silsSigan":"2","suupTypeNm":"일반","jehanInwon":"36\/34","suupTimes":"수(09:00-11:00)","suupRoomNms":"서울 올림픽체육관 316강의실","isuJehanYn":"O","suupTypeGb":"","banSosokNm":"체육학과","gnjSosokNm":"체육학과"},{"isuGrade":"2","banNo":"1","isuGbNm":"전공핵심","yungyukNm":"영역없음","suupNo2":"12162","haksuNo":"DCE2018","chgGwamokNm":"","gwamokNm":"운동생리1","suupMsg":"","abekGb":"N","hakwiNm":"학사","daepyoGangsaNm":"오상덕","hakjeom":"2","ironSigan":"2","silsSigan":"0","suupTypeNm":"일반","jehanInwon":"36\/33","suupTimes":"월(11:00-13:00)","suupRoomNms":"서울 올림픽체육관 316강의실","isuJehanYn":"O","suupTypeGb":"","banSosokNm":"체육학과","gnjSosokNm":"체육학과"},{"isuGrade":"3","banNo":"1","isuGbNm":"전공심화","yungyukNm":"영역없음","suupNo2":"12163","haksuNo":"DCE3005","chgGwamokNm":"","gwamokNm":"트레이닝방법론","suupMsg":"","abekGb":"N","hakwiNm":"학사","daepyoGangsaNm":"조중연","hakjeom":"2","ironSigan":"2","silsSigan":"0","suupTypeNm":"일반","jehanInwon":"15\/30","suupTimes":"수(11:00-13:00)","suupRoomNms":"서울 올림픽체육관 315강의실","isuJehanYn":"O","suupTypeGb":"","banSosokNm":"체육학과","gnjSosokNm":"체육학과"},{"isuGrade":"3","banNo":"1","isuGbNm":"전공핵심","yungyukNm":"영역없음","suupNo2":"12164","haksuNo":"DCE3030","chgGwamokNm":"","gwamokNm":"운동학습및제어","suupMsg":"","abekGb":"N","hakwiNm":"학사","daepyoGangsaNm":"김성민","hakjeom":"2","ironSigan":"2","silsSigan":"0","suupTypeNm":"일반","jehanInwon":"36\/30","suupTimes":"화(11:00-13:00)","suupRoomNms":"서울 올림픽체육관 315강의실","isuJehanYn":"O","suupTypeGb":"","banSosokNm":"체육학과","gnjSosokNm":"체육학과"},{"isuGrade":"3","banNo":"1","isuGbNm":"전공심화","yungyukNm":"영역없음","suupNo2":"12165","haksuNo":"DCE4005","chgGwamokNm":"","gwamokNm":"배드민턴","suupMsg":"","abekGb":"N","hakwiNm":"학사","daepyoGangsaNm":"정성용","hakjeom":"2","ironSigan":"0","silsSigan":"2","suupTypeNm":"일반","jehanInwon":"36\/33","suupTimes":"수(15:00-17:00)","suupRoomNms":"서울 올림픽체육관 220강의실","isuJehanYn":"O","suupTypeGb":"","banSosokNm":"체육학과","gnjSosokNm":"체육학과"},{"isuGrade":"3","banNo":"1","isuGbNm":"전공핵심","yungyukNm":"영역없음","suupNo2":"12166","haksuNo":"DCE4027","chgGwamokNm":"","gwamokNm":"운동처방","suupMsg":"","abekGb":"N","hakwiNm":"학사","daepyoGangsaNm":"오상덕","hakjeom":"3","ironSigan":"3","silsSigan":"0","suupTypeNm":"일반","jehanInwon":"17\/30","suupTimes":"금(11:00-12:30)\n목(15:00-16:30)","suupRoomNms":"서울 올림픽체육관 316강의실,서울 올림픽체육관 316강의실","isuJehanYn":"O","suupTypeGb":"","banSosokNm":"체육학과","gnjSosokNm":"체육학과"},{"isuGrade":"2","banNo":"1","isuGbNm":"전공심화","yungyukNm":"영역없음","suupNo2":"12169","haksuNo":"PHE1002","chgGwamokNm":"","gwamokNm":"체조","suupMsg":"","abekGb":"N","hakwiNm":"학사","daepyoGangsaNm":"임재영","hakjeom":"2","ironSigan":"0","silsSigan":"2","suupTypeNm":"일반","jehanInwon":"31\/30","suupTimes":"수(09:00-11:00)","suupRoomNms":"서울 올림픽체육관 어학실습실1","isuJehanYn":"O","suupTypeGb":"","banSosokNm":"체육학과","gnjSosokNm":"체육학과"},{"isuGrade":"1","banNo":"1","isuGbNm":"전공기초(필수)","yungyukNm":"영역없음","suupNo2":"12170","haksuNo":"PHE1036","chgGwamokNm":"","gwamokNm":"인체해부학","suupMsg":"","abekGb":"N","hakwiNm":"학사","daepyoGangsaNm":"김종희","hakjeom":"2","ironSigan":"2","silsSigan":"0","suupTypeNm":"일반","jehanInwon":"38\/34","suupTimes":"화(11:00-13:00)","suupRoomNms":"서울 올림픽체육관 316강의실","isuJehanYn":"O","suupTypeGb":"","banSosokNm":"체육학과","gnjSosokNm":"체육학과"},{"isuGrade":"1","banNo":"1","isuGbNm":"전공기초(필수)","yungyukNm":"영역없음","suupNo2":"12171","haksuNo":"PHE1041","chgGwamokNm":"","gwamokNm":"스포츠영어","suupMsg":"","abekGb":"N","hakwiNm":"학사","daepyoGangsaNm":"김종희","hakjeom":"2","ironSigan":"2","silsSigan":"0","suupTypeNm":"일반","jehanInwon":"33\/34","suupTimes":"월(13:00-15:00)","suupRoomNms":"서울 올림픽체육관 315강의실","isuJehanYn":"O","suupTypeGb":"영어전용","banSosokNm":"체육학과","gnjSosokNm":"체육학과"},{"isuGrade":"1","banNo":"1","isuGbNm":"전공핵심","yungyukNm":"영역없음","suupNo2":"12172","haksuNo":"PHE1043","chgGwamokNm":"","gwamokNm":"건강과질병의이해","suupMsg":"","abekGb":"N","hakwiNm":"학사","daepyoGangsaNm":"김종희","hakjeom":"2","ironSigan":"2","silsSigan":"0","suupTypeNm":"일반","jehanInwon":"37\/34","suupTimes":"화(15:00-17:00)","suupRoomNms":"서울 올림픽체육관 314강의실","isuJehanYn":"O","suupTypeGb":"","banSosokNm":"체육학과","gnjSosokNm":"체육학과"},{"isuGrade":"1","banNo":"1","isuGbNm":"전공기초(필수)","yungyukNm":"영역없음","suupNo2":"12173","haksuNo":"PHE1045","chgGwamokNm":"","gwamokNm":"기초실기1","suupMsg":"","abekGb":"N","hakwiNm":"학사","daepyoGangsaNm":"김종희","hakjeom":"1","ironSigan":"0","silsSigan":"1","suupTypeNm":"일반","jehanInwon":"32\/32","suupTimes":"수(17:00-18:00)","suupRoomNms":"서울 올림픽체육관 220강의실","isuJehanYn":"O","suupTypeGb":"","banSosokNm":"체육학과","gnjSosokNm":"체육학과"},{"isuGrade":"1","banNo":"1","isuGbNm":"전공기초(필수)","yungyukNm":"영역없음","suupNo2":"12174","haksuNo":"PHE2017","chgGwamokNm":"","gwamokNm":"육상","suupMsg":"","abekGb":"N","hakwiNm":"학사","daepyoGangsaNm":"이성직","hakjeom":"2","ironSigan":"0","silsSigan":"2","suupTypeNm":"일반","jehanInwon":"33\/32","suupTimes":"목(09:00-11:00)","suupRoomNms":"서울 올림픽체육관 220강의실","isuJehanYn":"O","suupTypeGb":"","banSosokNm":"체육학과","gnjSosokNm":"체육학과"},{"isuGrade":"2","banNo":"1","isuGbNm":"전공심화","yungyukNm":"영역없음","suupNo2":"12175","haksuNo":"PHE2018","chgGwamokNm":"","gwamokNm":"배구","suupMsg":"","abekGb":"N","hakwiNm":"학사","daepyoGangsaNm":"양진웅","hakjeom":"2","ironSigan":"0","silsSigan":"2","suupTypeNm":"일반","jehanInwon":"40\/33","suupTimes":"화(15:00-17:00)","suupRoomNms":"서울 올림픽체육관 220강의실","isuJehanYn":"O","suupTypeGb":"","banSosokNm":"체육학과","gnjSosokNm":"체육학과"},{"isuGrade":"2","banNo":"1","isuGbNm":"전공기초(필수)","yungyukNm":"영역없음","suupNo2":"12178","haksuNo":"PHE2101","chgGwamokNm":"","gwamokNm":"기초실기3","suupMsg":"","abekGb":"N","hakwiNm":"학사","daepyoGangsaNm":"김성민","hakjeom":"1","ironSigan":"0","silsSigan":"1","suupTypeNm":"일반","jehanInwon":"35\/35","suupTimes":"수(18:00-19:00)","suupRoomNms":"서울 올림픽체육관 220강의실","isuJehanYn":"O","suupTypeGb":"","banSosokNm":"체육학과","gnjSosokNm":"체육학과"},{"isuGrade":"3","banNo":"1","isuGbNm":"전공기초(필수)","yungyukNm":"영역없음","suupNo2":"12180","haksuNo":"PHE3100","chgGwamokNm":"","gwamokNm":"기초실기5","suupMsg":"","abekGb":"N","hakwiNm":"학사","daepyoGangsaNm":"이성노","hakjeom":"1","ironSigan":"0","silsSigan":"1","suupTypeNm":"일반","jehanInwon":"30\/30","suupTimes":"수(18:00-19:00)","suupRoomNms":"서울 올림픽체육관 314강의실","isuJehanYn":"O","suupTypeGb":"","banSosokNm":"체육학과","gnjSosokNm":"체육학과"},{"isuGrade":"2","banNo":"1","isuGbNm":"전공심화","yungyukNm":"영역없음","suupNo2":"12181","haksuNo":"PHE4006","chgGwamokNm":"","gwamokNm":"테니스","suupMsg":"","abekGb":"N","hakwiNm":"학사","daepyoGangsaNm":"윤종웅","hakjeom":"2","ironSigan":"0","silsSigan":"2","suupTypeNm":"일반","jehanInwon":"34\/34","suupTimes":"화(09:00-11:00)","suupRoomNms":"서울 올림픽체육관 어학실습실1","isuJehanYn":"O","suupTypeGb":"","banSosokNm":"체육학과","gnjSosokNm":"체육학과"},{"isuGrade":"3","banNo":"1","isuGbNm":"전공심화","yungyukNm":"영역없음","suupNo2":"12182","haksuNo":"PHE4026","chgGwamokNm":"","gwamokNm":"특수체육","suupMsg":"","abekGb":"N","hakwiNm":"학사","daepyoGangsaNm":"김성민","hakjeom":"2","ironSigan":"2","silsSigan":"0","suupTypeNm":"일반","jehanInwon":"12\/30","suupTimes":"수(13:00-15:00)","suupRoomNms":"서울 올림픽체육관 315강의실","isuJehanYn":"O","suupTypeGb":"","banSosokNm":"체육학과","gnjSosokNm":"체육학과"},{"isuGrade":"1","banNo":"1","isuGbNm":"전공기초(필수)","yungyukNm":"영역없음","suupNo2":"12183","haksuNo":"PHE4086","chgGwamokNm":"","gwamokNm":"스포츠와인체기능학","suupMsg":"","abekGb":"N","hakwiNm":"학사","daepyoGangsaNm":"박양선","hakjeom":"2","ironSigan":"2","silsSigan":"0","suupTypeNm":"일반","jehanInwon":"37\/34","suupTimes":"화(13:00-15:00)","suupRoomNms":"서울 올림픽체육관 316강의실","isuJehanYn":"O","suupTypeGb":"","banSosokNm":"체육학과","gnjSosokNm":"체육학과"},{"isuGrade":"2","banNo":"1","isuGbNm":"전공심화","yungyukNm":"영역없음","suupNo2":"12184","haksuNo":"PHE4088","chgGwamokNm":"","gwamokNm":"체육측정법","suupMsg":"","abekGb":"N","hakwiNm":"학사","daepyoGangsaNm":"이성노","hakjeom":"2","ironSigan":"2","silsSigan":"0","suupTypeNm":"일반","jehanInwon":"30\/31","suupTimes":"화(13:00-15:00)","suupRoomNms":"서울 올림픽체육관 314강의실","isuJehanYn":"O","suupTypeGb":"","banSosokNm":"체육학과","gnjSosokNm":"체육학과"},{"isuGrade":"3","banNo":"1","isuGbNm":"전공핵심","yungyukNm":"영역없음","suupNo2":"12185","haksuNo":"PHE5021","chgGwamokNm":"","gwamokNm":"스포츠통계학1","suupMsg":"","abekGb":"N","hakwiNm":"학사","daepyoGangsaNm":"이태현","hakjeom":"2","ironSigan":"2","silsSigan":"0","suupTypeNm":"일반","jehanInwon":"26\/30","suupTimes":"월(15:00-17:00)","suupRoomNms":"서울 올림픽체육관 314강의실","isuJehanYn":"O","suupTypeGb":"","banSosokNm":"체육학과","gnjSosokNm":"체육학과"},{"isuGrade":"2","banNo":"1","isuGbNm":"전공핵심","yungyukNm":"영역없음","suupNo2":"12186","haksuNo":"PHE5033","chgGwamokNm":"","gwamokNm":"스포츠영양학","suupMsg":"","abekGb":"N","hakwiNm":"학사","daepyoGangsaNm":"정재훈","hakjeom":"2","ironSigan":"2","silsSigan":"0","suupTypeNm":"일반","jehanInwon":"42\/36","suupTimes":"수(11:00-13:00)","suupRoomNms":"서울 올림픽체육관 어학실습실1","isuJehanYn":"O","suupTypeGb":"","banSosokNm":"체육학과","gnjSosokNm":"체육학과"},{"isuGrade":"3","banNo":"1","isuGbNm":"교직전공","yungyukNm":"영역없음","suupNo2":"12189","haksuNo":"TEA5017","chgGwamokNm":"","gwamokNm":"체육교과교육론","suupMsg":"","abekGb":"N","hakwiNm":"학사","daepyoGangsaNm":"김정구","hakjeom":"3","ironSigan":"3","silsSigan":"0","suupTypeNm":"일반","jehanInwon":"5\/30","suupTimes":"화(17:00-18:30)\n화(18:30-20:00)","suupRoomNms":"서울 올림픽체육관 226강의실,서울 올림픽체육관 226강의실","isuJehanYn":"O","suupTypeGb":"","banSosokNm":"체육학과","gnjSosokNm":"체육학과"}]